{
  "slug": "vietnam-3-week-itinerary-autumn",
  "title": "Vietnam 3-Week Itinerary – Autumn 2026",
  "excerpt": "Experience Vietnam's golden harvest season while avoiding typhoons. This 21-day route covers North Vietnam in depth, skips stormy Central, and ends in the sunny south.",
  "content": "# Vietnam 3-Week Itinerary – Autumn 2026\n\nAutumn in Vietnam requires strategic routing — Central Vietnam's typhoons are dangerous, but the north is at its best and the south is clearing up. This 21-day route digs deep into North Vietnam's golden rice harvest, then flies south for Mekong rivers and Phu Quoc beaches.\n\n## Quick Facts\n\n- **Duration:** 21 days / 20 nights\n- **Best Months:** September through November\n- **Regions Covered:** North Vietnam (in depth), South Vietnam\n- **Internal Flights:** 1 (Hanoi → HCMC)\n- **Pace:** Relaxed\n- **Budget Range:** $45-90 per day\n\n## Why Autumn Works (With Caution)\n\nAutumn is the north's best season — golden rice terraces, clear skies, comfortable temperatures (20-28°C). The south is transitioning out of monsoon, with improving conditions through the season.\n\n**Critical warning:** Central Vietnam (Hue, Hoi An, Da Nang) has typhoons September-November. Flooding, cancelled flights, dangerous conditions. This route skips Central entirely.\n\n## Day-by-Day Itinerary\n\n### [Hanoi](/vietnam/destinations/hanoi) (3 nights)\n\nAutumn Hanoi is perfect — 24-26°C, low humidity, blue skies. The Old Quarter feels relaxed rather than oppressive. Explore without rushing: temples, museums, street food, coffee culture.\n\nUse day three to prepare for Ha Giang — rent a motorbike or arrange a driver.\n\n**Highlights:** Old Quarter, Temple of Literature, autumn walking weather\n\n### [Ha Giang](/vietnam/destinations/ha-giang) (4 nights)\n\nDrive north to Ha Giang (6-7 hours) for Vietnam's most dramatic scenery. The Ha Giang Loop winds through karst mountains, terraced valleys, and ethnic minority villages. Autumn brings golden rice at lower elevations and buckwheat flowers on the peaks.\n\nThis is challenging but unforgettable travel — Vietnam's last frontier. Hire a driver if you're not confident on mountain roads.\n\n*Travel from Hanoi: 6-7 hours by bus or car, $15-50.*\n\n**Highlights:** Ha Giang Loop, Ma Pi Leng Pass, golden terraces, minority villages\n\n### [Sapa](/vietnam/destinations/sapa) (3 nights)\n\nDrive west to Sapa (5-6 hours). After Ha Giang's adventure, Sapa feels almost civilized. September brings golden terraces before harvest; October means harvest activity; November shows bare fields and clear views.\n\nTrek to villages, take the Fansipan cable car, enjoy mountain evenings.\n\n*Travel from Ha Giang: 5-6 hours by car.*\n\n**Highlights:** Rice terraces, trekking, mountain views\n\n### Hanoi (1 night)\n\nReturn to Hanoi (5-6 hours) for a city night. Rest, laundry, favorite spots revisited.\n\n### [Ninh Binh](/vietnam/destinations/ninh-binh) (2 nights)\n\nHead south to Ninh Binh (2 hours) for the famous \"Ha Long Bay on land\" landscapes. Late September-October means golden rice harvest — the karsts rising from golden paddies are iconic.\n\nTam Coc boat rides, Mua Cave viewpoint, cycling.\n\n*Travel from Hanoi: 2 hours by car or bus.*\n\n**Highlights:** Golden harvest, Tam Coc, Mua Cave\n\n### [Ha Long Bay](/vietnam/destinations/ha-long-bay) (2 nights)\n\nContinue to Ha Long Bay (3-4 hours) for a 2-night cruise. Autumn brings clear skies and calm seas — excellent kayaking and swimming conditions.\n\n*Travel from Ninh Binh: 3-4 hours by car.*\n\n**Highlights:** Autumn clarity, calm seas, uncrowded caves\n\n### [Ho Chi Minh City](/vietnam/destinations/ho-chi-minh-city) (2 nights)\n\nFly from Hanoi to HCMC (2 hours). The south is emerging from monsoon season — expect some afternoon rain but improving conditions. Two nights covers the essentials: War Remnants Museum, Chinatown, rooftop bars.\n\n*Travel from Ha Long Bay: Return to Hanoi (3-4 hours), then 2-hour flight.*\n\n**Highlights:** War Remnants Museum, city energy, evening food scene\n\n### [Mekong Delta](/vietnam/destinations/mekong-delta) (2 nights)\n\nHead to Can Tho (3.5 hours) for the Mekong's floating markets and river life. Water levels are manageable in autumn; boat tours operate smoothly. Cai Rang Floating Market at dawn is unmissable.\n\n*Travel from HCMC: 3.5 hours by car or bus.*\n\n**Highlights:** Cai Rang Floating Market, river life, delta homestay\n\n### [Phu Quoc](/vietnam/destinations/phu-quoc) (4 nights)\n\nFly from Can Tho (or HCMC) to Phu Quoc. By November, the island is in full dry-season mode — sunshine, calm seas, perfect beach weather. End your trip unwinding.\n\n*Travel from Mekong: 45-minute flight from Can Tho or return to HCMC.*\n\n**Highlights:** Beach relaxation, seafood, island exploring\n\n## Why This Itinerary Works\n\n**Avoiding typhoons:** Central Vietnam is dangerous September-November. This route skips it entirely — your safety and enjoyment matter more than checking boxes.\n\n**Northern depth:** Most visitors rush through the north. Four nights in Ha Giang and three in Sapa let you experience the region properly.\n\n**Timing the south:** By November, the south's monsoon is ending. Phu Quoc is entering peak season.\n\n## Adjustments\n\n**Late November:** The south is at its best; consider extending Phu Quoc and Mekong, shortening the north.\n\n**Skip Ha Giang:** If the adventure is too much, extend Sapa (5 nights) and add [Cat Ba Island](/vietnam/destinations/cat-ba) instead.\n\n**Check conditions:** If typhoons are severe, the south may have residual flooding. Monitor weather and be flexible.\n\n## FAQ\n\n**Why can't I visit Hoi An in autumn?**\n\nTyphoon season. September-November brings severe storms, flooding, and dangerous conditions. Flights cancel, roads flood, beaches close. It's genuinely risky — don't chance it.\n\n**Is Ha Giang safe in autumn?**\n\nYes — the north doesn't get typhoons. Roads can be wet after rain but nothing compared to central Vietnam. Hire an experienced driver if you're concerned.\n\n**When is rice harvest in Sapa?**\n\nEarly September in the higher terraces, late September-October lower down. By November, most rice is cut. Plan accordingly for golden terraces vs. clear views.\n\n**What if I only have 2 weeks?**\n\nFocus on North Vietnam only — Hanoi, Ha Giang, Sapa, Ninh Binh, Ha Long Bay. Skip the south entirely. See our 2-week autumn itinerary.",
  "metaTitle": "Vietnam 3-Week Itinerary Autumn 2026 | Golden Harvest Route",
  "metaDescription": "Experience Vietnam's golden rice harvest while avoiding typhoons. 21-day North Vietnam and South Vietnam route for September-November.",
  "keywords": [
    "vietnam 3 week autumn itinerary",
    "vietnam fall travel",
    "vietnam rice harvest",
    "vietnam typhoon season",
    "ha giang autumn",
    "vietnam september october november",
    "avoid vietnam typhoons",
    "vietnam 21 days autumn"
  ],
  "canonicalUrl": "https://vietnamtravel.com/vietnam/itineraries/vietnam-3-week-itinerary-autumn",
  "ogImage": "/images/itineraries/vietnam-3-week-autumn.jpg",
  "author": "Vietnam Travel Guide",
  "itineraryMeta": {
    "duration": "3-week",
    "days": 21,
    "season": "autumn",
    "months": [
      "September",
      "October",
      "November"
    ],
    "regions": [
      "north",
      "south"
    ],
    "internalFlights": 1,
    "pace": "relaxed",
    "budgetRange": {
      "min": 45,
      "max": 90,
      "currency": "USD",
      "perDay": true
    }
  },
  "route": {
    "entryCity": "hanoi",
    "exitCity": "phu-quoc",
    "direction": "north-to-south",
    "stops": [
      {
        "slug": "hanoi",
        "nights": 3,
        "dayTrips": []
      },
      {
        "slug": "ha-giang",
        "nights": 4,
        "dayTrips": []
      },
      {
        "slug": "sapa",
        "nights": 3,
        "dayTrips": []
      },
      {
        "slug": "hanoi",
        "nights": 1,
        "dayTrips": []
      },
      {
        "slug": "ninh-binh",
        "nights": 2,
        "dayTrips": []
      },
      {
        "slug": "ha-long-bay",
        "nights": 2,
        "dayTrips": []
      },
      {
        "slug": "ho-chi-minh-city",
        "nights": 2,
        "dayTrips": []
      },
      {
        "slug": "mekong-delta",
        "nights": 2,
        "dayTrips": []
      },
      {
        "slug": "phu-quoc",
        "nights": 4,
        "dayTrips": []
      }
    ]
  },
  "contentMeta": {
    "wordCount": 980,
    "readingTime": 5,
    "internalLinks": [
      "/vietnam/destinations/hanoi",
      "/vietnam/destinations/ha-giang",
      "/vietnam/destinations/sapa",
      "/vietnam/destinations/ninh-binh",
      "/vietnam/destinations/ha-long-bay",
      "/vietnam/destinations/ho-chi-minh-city",
      "/vietnam/destinations/mekong-delta",
      "/vietnam/destinations/phu-quoc",
      "/vietnam/destinations/cat-ba"
    ]
  },
  "faq": [
    {
      "question": "Why can't I visit Hoi An in autumn?",
      "answer": "Typhoon season. September-November brings severe storms, flooding, and dangerous conditions. Flights cancel, roads flood, beaches close. It's genuinely risky — don't chance it."
    },
    {
      "question": "Is Ha Giang safe in autumn?",
      "answer": "Yes — the north doesn't get typhoons. Roads can be wet after rain but nothing compared to central Vietnam. Hire an experienced driver if you're concerned."
    },
    {
      "question": "When is rice harvest in Sapa?",
      "answer": "Early September in the higher terraces, late September-October lower down. By November, most rice is cut. Plan accordingly for golden terraces vs. clear views."
    },
    {
      "question": "What if I only have 2 weeks?",
      "answer": "Focus on North Vietnam only — Hanoi, Ha Giang, Sapa, Ninh Binh, Ha Long Bay. Skip the south entirely. See our 2-week autumn itinerary."
    }
  ],
  "status": "draft",
  "publishedAt": null,
  "agentWorkflow": {
    "generatedBy": "agent",
    "generatedAt": "2026-01-27T00:00:00.000Z"
  }
}
