{
  "slug": "vietnam-3-week-itinerary-winter",
  "title": "Vietnam 3-Week Itinerary – Winter 2026",
  "excerpt": "Escape winter cold with this 21-day Vietnam journey. Brief Hanoi, charming Hoi An, vibrant HCMC, and sunny Phu Quoc beaches — south gets the best weather.",
  "content": "# Vietnam 3-Week Itinerary – Winter 2026\n\nWinter in Vietnam means heading south. While the north shivers under gray skies, Central and South Vietnam bask in dry-season perfection. This 21-day route includes a brief taste of Hanoi, then moves to where the weather rewards you — Hoi An's lanterns, HCMC's energy, and Phu Quoc's beaches.\n\n## Quick Facts\n\n- **Duration:** 21 days / 20 nights\n- **Best Months:** December through February\n- **Regions Covered:** North (brief), Central, South Vietnam\n- **Internal Flights:** 2 (Hanoi → Da Nang, HCMC → Phu Quoc)\n- **Pace:** Relaxed\n- **Budget Range:** $55-110 per day\n\n## Why Winter Works\n\nDecember-February is the south's dry season — sunny days, 28-32°C, perfect beaches. Central Vietnam is mild (20-25°C) with occasional drizzle but no typhoons. The north is cold (10-15°C in Hanoi) and often gray, so we keep it brief.\n\nThis route prioritizes warmth and sunshine.\n\n## Day-by-Day Itinerary\n\n### [Hanoi](/vietnam/destinations/hanoi) (2 nights)\n\nStart in Vietnam's capital for a cultural introduction, but don't linger — winter Hanoi is 10-15°C with gray, drizzly days. Two nights is enough for the Old Quarter essentials: Hoan Kiem Lake, Temple of Literature, street food.\n\nPack warm layers and embrace the cozy side — this is excellent pho weather.\n\n**Highlights:** Old Quarter, Temple of Literature, warming street food\n\n### [Hue](/vietnam/destinations/hue) (2 nights)\n\nFly to Hue (1.5 hours). Vietnam's former imperial capital is cool but comfortable in winter (18-22°C). The Citadel feels contemplative in the quieter season, and royal tomb visits are crowd-free.\n\nOccasional drizzle is possible — pack a light jacket. The city's reflective atmosphere suits the weather.\n\n*Travel from Hanoi: 1.5-hour flight, $50-80.*\n\n**Highlights:** Imperial Citadel, Royal Tombs, Thien Mu Pagoda\n\n### [Hoi An](/vietnam/destinations/hoi-an) (5 nights)\n\nDrive the scenic Hai Van Pass to Hoi An (3-4 hours). Five nights lets you fully experience this UNESCO town — get clothes made (budget 2-3 days for fittings), take a cooking class, explore the Old Town, and day trip to [Da Nang](/vietnam/destinations/da-nang) and My Son ruins.\n\nWinter Hoi An is 20-25°C with occasional light rain. The beach isn't peak swimming season but the town itself is magical — fewer tourists, cooler evenings, lanterns glowing brighter.\n\n*Travel from Hue: 3-4 hours by car (Hai Van Pass).*\n\n**Highlights:** Tailoring, Old Town, cooking class, uncrowded temples\n\n### [Ho Chi Minh City](/vietnam/destinations/ho-chi-minh-city) (3 nights)\n\nFly from Da Nang to HCMC (1.5 hours). Winter HCMC is warm (28-32°C) and dry — perfect for exploring. The War Remnants Museum, Chinatown, rooftop bars, and legendary street food scene.\n\nDay trip to Cu Chi Tunnels or save energy for the Mekong.\n\n*Travel from Hoi An: 45-minute transfer to Da Nang, 1.5-hour flight.*\n\n**Highlights:** War Remnants Museum, rooftop bars, street food, Cu Chi Tunnels\n\n### [Mekong Delta](/vietnam/destinations/mekong-delta) (2 nights)\n\nHead to Can Tho (3.5 hours) for the delta's floating markets and river life. Winter is dry season — calm waters, easy boat travel, and Cai Rang Floating Market at its best.\n\nStay in a riverside homestay for the authentic experience. Wake at 5am for the market.\n\n*Travel from HCMC: 3.5 hours by car or bus.*\n\n**Highlights:** Cai Rang Floating Market, river homestay, delta life\n\n### [Phu Quoc](/vietnam/destinations/phu-quoc) (6 nights)\n\nFly to Phu Quoc (45 minutes from Can Tho or 1 hour from HCMC) for six nights of beach unwinding. This is peak season: sunny, calm seas, perfect conditions.\n\nSix nights means you can truly relax. Beach days, motorbike exploration, pepper farm visits, night market seafood. No agenda, no rushing.\n\n*Travel from Mekong: 45-minute flight from Can Tho (or return to HCMC).*\n\n**Highlights:** Peak beach season, seafood, island exploring, sunsets\n\n## Why This Itinerary Works\n\n**Weather optimization:** Most time where weather is best (Central and South). Brief Hanoi for cultural context, then warmth.\n\n**Extended beach:** Six nights on Phu Quoc during peak season is a proper beach holiday, not a rushed visit.\n\n**Balanced culture:** Hoi An and Hue provide history and charm before HCMC's energy and Phu Quoc's relaxation.\n\n## Adjustments\n\n**Skip Hanoi:** Fly direct to Da Nang and start in Hoi An if you want maximum warmth. You'll miss Hanoi's unique character but gain better weather.\n\n**Add Da Lat:** Insert 2 nights in [Da Lat](/vietnam/destinations/da-lat) (cooler highlands) between HCMC and Phu Quoc for mountain contrast.\n\n**Different island:** Replace Phu Quoc with [Con Dao](/vietnam/destinations/con-dao) for better snorkeling and fewer tourists, or [Mui Ne](/vietnam/destinations/mui-ne) for kite surfing.\n\n## FAQ\n\n**Is Hanoi worth visiting in winter?**\n\nFor a brief cultural introduction, yes. But don't expect comfortable outdoor weather — 10-15°C, gray skies, and drizzle are common. Two nights is enough; more would feel gloomy.\n\n**What's Hoi An like in winter?**\n\nCool (20-25°C) with occasional light rain, but charming. The Old Town is less crowded, tailors have more time, and evening lanterns glow against moody skies. Beach swimming is marginal but town exploration is excellent.\n\n**Is Phu Quoc crowded in winter?**\n\nYes — it's peak season. Book accommodation 3-4 weeks ahead for best selection. Prices are higher than shoulder season, but weather is guaranteed good.\n\n**What if I want to see Ha Long Bay?**\n\nPossible but expect cold, gray conditions and limited visibility. Cruises run year-round but winter isn't ideal. Save it for a spring or autumn trip when conditions are better.",
  "metaTitle": "Vietnam 3-Week Itinerary Winter 2026 | Sunshine South Route",
  "metaDescription": "Escape winter with this 21-day Vietnam route. Brief Hanoi, charming Hoi An, vibrant HCMC, and 6 nights of Phu Quoc beaches. December-February guide.",
  "keywords": [
    "vietnam 3 week winter itinerary",
    "vietnam winter travel",
    "vietnam december january february",
    "vietnam escape cold",
    "phu quoc winter",
    "vietnam dry season",
    "vietnam 21 days winter",
    "hoi an phu quoc itinerary"
  ],
  "canonicalUrl": "https://vietnamtravel.com/vietnam/itineraries/vietnam-3-week-itinerary-winter",
  "ogImage": "/images/itineraries/vietnam-3-week-winter.jpg",
  "author": "Vietnam Travel Guide",
  "itineraryMeta": {
    "duration": "3-week",
    "days": 21,
    "season": "winter",
    "months": [
      "December",
      "January",
      "February"
    ],
    "regions": [
      "north",
      "central",
      "south"
    ],
    "internalFlights": 2,
    "pace": "relaxed",
    "budgetRange": {
      "min": 55,
      "max": 110,
      "currency": "USD",
      "perDay": true
    }
  },
  "route": {
    "entryCity": "hanoi",
    "exitCity": "phu-quoc",
    "direction": "north-to-south",
    "stops": [
      {
        "slug": "hanoi",
        "nights": 2,
        "dayTrips": []
      },
      {
        "slug": "hue",
        "nights": 2,
        "dayTrips": []
      },
      {
        "slug": "hoi-an",
        "nights": 5,
        "dayTrips": [
          "da-nang"
        ]
      },
      {
        "slug": "ho-chi-minh-city",
        "nights": 3,
        "dayTrips": []
      },
      {
        "slug": "mekong-delta",
        "nights": 2,
        "dayTrips": []
      },
      {
        "slug": "phu-quoc",
        "nights": 6,
        "dayTrips": []
      }
    ]
  },
  "contentMeta": {
    "wordCount": 980,
    "readingTime": 5,
    "internalLinks": [
      "/vietnam/destinations/hanoi",
      "/vietnam/destinations/hue",
      "/vietnam/destinations/hoi-an",
      "/vietnam/destinations/da-nang",
      "/vietnam/destinations/ho-chi-minh-city",
      "/vietnam/destinations/mekong-delta",
      "/vietnam/destinations/phu-quoc",
      "/vietnam/destinations/da-lat",
      "/vietnam/destinations/con-dao",
      "/vietnam/destinations/mui-ne"
    ]
  },
  "faq": [
    {
      "question": "Is Hanoi worth visiting in winter?",
      "answer": "For a brief cultural introduction, yes. But don't expect comfortable outdoor weather — 10-15°C, gray skies, and drizzle are common. Two nights is enough; more would feel gloomy."
    },
    {
      "question": "What's Hoi An like in winter?",
      "answer": "Cool (20-25°C) with occasional light rain, but charming. The Old Town is less crowded, tailors have more time, and evening lanterns glow against moody skies. Beach swimming is marginal but town exploration is excellent."
    },
    {
      "question": "Is Phu Quoc crowded in winter?",
      "answer": "Yes — it's peak season. Book accommodation 3-4 weeks ahead for best selection. Prices are higher than shoulder season, but weather is guaranteed good."
    },
    {
      "question": "What if I want to see Ha Long Bay?",
      "answer": "Possible but expect cold, gray conditions and limited visibility. Cruises run year-round but winter isn't ideal. Save it for a spring or autumn trip when conditions are better."
    }
  ],
  "status": "draft",
  "publishedAt": null,
  "agentWorkflow": {
    "generatedBy": "agent",
    "generatedAt": "2026-01-27T00:00:00.000Z"
  }
}
